http_use/__init__.py
http_use/py.typed
http_use-0.1.3.dist-info/METADATA
http_use-0.1.3.dist-info/WHEEL
http_use-0.1.3.dist-info/RECORD
