Metadata-Version: 2.4
Name: http-use
Version: 0.1.3
Summary: Ultra efficient web scraper developped on demand
Project-URL: Homepage, https://github.com/grll/http-use
Project-URL: Repository, https://github.com/grll/http-use
Author-email: Guillaume Raille <guillaume.raille@gmail.com>
License-Expression: MIT
Classifier: Intended Audience :: Developers
Classifier: License :: OSI Approved :: MIT License
Classifier: Operating System :: OS Independent
Classifier: Programming Language :: Python :: 3.13
Classifier: Topic :: Software Development :: Libraries :: Python Modules
Classifier: Typing :: Typed
Requires-Python: >=3.13
